cortefy/README.md
cortefy/__init__.py
cortefy/client.py
cortefy/exceptions.py
cortefy/resources/__init__.py
cortefy/resources/memories.py
cortefy/resources/search.py
cortefy-0.1.4.dist-info/METADATA
cortefy-0.1.4.dist-info/WHEEL
cortefy-0.1.4.dist-info/top_level.txt
cortefy-0.1.4.dist-info/RECORD
